baler_control_plane/__about__.py
baler_control_plane/__init__.py
baler_control_plane/app.py
baler_control_plane-0.0.1.dev0.dist-info/METADATA
baler_control_plane-0.0.1.dev0.dist-info/WHEEL
baler_control_plane-0.0.1.dev0.dist-info/licenses/LICENSE.md
baler_control_plane-0.0.1.dev0.dist-info/RECORD
