Metadata-Version: 2.3
Name: baler-control-plane
Version: 0.0.1.dev0
Summary: Application for managing baler-operator agents.
Author-email: Greg Nagy <greg@gatecastle.com>
License: 
License-File: LICENSE.md
Keywords: baler,baler-control-plane,haystack,kubernetes,nlp,operator
Classifier: License :: OSI Approved :: Apache Software License
Classifier: Operating System :: OS Independent
Classifier: Programming Language :: Python :: 3
Requires-Python: >=3.8
Requires-Dist: flask-sqlalchemy==3.1.1
Requires-Dist: flask==3.0.3
Provides-Extra: dev
Requires-Dist: myst-parser; extra == 'dev'
Requires-Dist: sphinx-rtd-theme; extra == 'dev'
Requires-Dist: sphinx==7.2.6; extra == 'dev'
